{
    "keydown": {
        "W": {
            "callback": "player1.change_movement",
            "args": [0, -1, true]
        },
        "S": {
            "callback": "player1.change_movement",
            "args": [0, 1, true]
        },
        "A": {
            "callback": "player1.change_movement",
            "args": [-1, 0, true]
        },
        "D": {
            "callback": "player1.change_movement",
            "args": [1, 0, true]
        },
        "ONE": {
            "callback": "player1.try_dropping_bomb"
        },
        "NUMPAD_8": {
            "callback": "player2.change_movement",
            "args": [0, -1, true]
        },
        "NUMPAD_5": {
            "callback": "player2.change_movement",
            "args": [0, 1, true]
        },
        "NUMPAD_4": {
            "callback": "player2.change_movement",
            "args": [-1, 0, true]
        },
        "NUMPAD_6": {
            "callback": "player2.change_movement",
            "args": [1, 0, true]
        },
        "NUMPAD_0": {
            "callback": "player2.try_dropping_bomb"
        }
    },
    "keyup": {
        "W": {
            "callback": "player1.change_movement",
            "args": [0, -1, false]
        },
        "S": {
            "callback": "player1.change_movement",
            "args": [0, 1, false]
        },
        "A": {
            "callback": "player1.change_movement",
            "args": [-1, 0, false]
        },
        "D": {
            "callback": "player1.change_movement",
            "args": [1, 0, false]
        },
        "NUMPAD_8": {
            "callback": "player2.change_movement",
            "args": [0, -1, false]
        },
        "NUMPAD_5": {
            "callback": "player2.change_movement",
            "args": [0, 1, false]
        },
        "NUMPAD_4": {
            "callback": "player2.change_movement",
            "args": [-1, 0, false]
        },
        "NUMPAD_6": {
            "callback": "player2.change_movement",
            "args": [1, 0, false]
        }
    }
}